spicejack/__init__.py
spicejack/base_processor.py
spicejack/chatbot.py
spicejack/pdf.py
spicejack/prompt.py
spicejack-0.45b0.dist-info/LICENSE
spicejack-0.45b0.dist-info/METADATA
spicejack-0.45b0.dist-info/WHEEL
spicejack-0.45b0.dist-info/top_level.txt
spicejack-0.45b0.dist-info/RECORD
