Metadata-Version: 2.1
Name: spicejack
Version: 0.45b0
Summary: Python package for generating training data from documents.
Home-page: https://github.com/LIZARD-OFFICIAL-77/SpiceJack
Author: LIZARD-OFFICIAL-77
Author-email: <lizard.official.77@gmail.com>
License: 
Project-URL: Source Code, https://github.com/LIZARD-OFFICIAL-77/SpiceJack
Project-URL: Bug Tracker, https://github.com/LIZARD-OFFICIAL-77/SpiceJack/issues
Keywords: python,json,chatbot,reverse-engineering,openai,chatbots,gpt,language-model,gpt-3,gpt3,openai-api,gpt-4,gpt4,chatgpt,chatgpt-api,openai-chatgpt,chatgpt-free,chatgpt-4,chatgpt4,chatgpt4-api,free,free-gpt,gpt4free,g4f,openai
Classifier: Development Status :: 2 - Pre-Alpha
Classifier: Intended Audience :: Developers
Classifier: Programming Language :: Python :: 3
Classifier: Operating System :: Unix
Classifier: Operating System :: MacOS :: MacOS X
Classifier: Operating System :: Microsoft :: Windows
License-File: LICENSE
Requires-Dist: g4f
Requires-Dist: pdfminer.six
Requires-Dist: python-dotenv
Requires-Dist: openai
